pgsql_wrapper.py
setup.py
pgsql_wrapper.egg-info/PKG-INFO
pgsql_wrapper.egg-info/SOURCES.txt
pgsql_wrapper.egg-info/dependency_links.txt
pgsql_wrapper.egg-info/requires.txt
pgsql_wrapper.egg-info/top_level.txt
pgsql_wrapper.egg-info/zip-safe