Metadata-Version: 1.0
Name: pgsql-wrapper
Version: 1.1.1
Summary: PostgreSQL / psycopg2 caching wrapper class
Home-page: http://github.com/MeetMe/pgsql_wrapper
Author: Gavin M. Roy
Author-email: gmr@meetme.com
License: UNKNOWN
Platform: UNKNOWN
